serialite/__init__.py
serialite/_base.py
serialite/_dataclass.py
serialite/_decorators.py
serialite/_descriptors.py
serialite/_dispatcher.py
serialite/_errors.py
serialite/_field_errors.py
serialite/_fields_serializer.py
serialite/_implementations/__init__.py
serialite/_implementations/_array.py
serialite/_implementations/_boolean.py
serialite/_implementations/_date_time.py
serialite/_implementations/_dictionary.py
serialite/_implementations/_float.py
serialite/_implementations/_integer.py
serialite/_implementations/_json.py
serialite/_implementations/_list.py
serialite/_implementations/_literal.py
serialite/_implementations/_none.py
serialite/_implementations/_ordered_set.py
serialite/_implementations/_path.py
serialite/_implementations/_reserved.py
serialite/_implementations/_set.py
serialite/_implementations/_string.py
serialite/_implementations/_tuple.py
serialite/_implementations/_union.py
serialite/_implementations/_uuid.py
serialite/_mixins.py
serialite/_monkey_patches.py
serialite/_numeric_check.py
serialite/_openapi.py
serialite/_result.py
serialite/_type_errors.py
serialite-0.5.1.dist-info/licenses/LICENSE
serialite-0.5.1.dist-info/WHEEL
serialite-0.5.1.dist-info/METADATA
serialite-0.5.1.dist-info/RECORD
