Metadata-Version: 2.4
Name: serialite
Version: 0.5.1
Summary: A serialization library for Python
Keywords: serialization,deserialization,serde,pydantic,fastapi
Author: David Hagen
Author-email: David Hagen <david@drhagen.com>
License-Expression: MIT
License-File: LICENSE
Classifier: Development Status :: 4 - Beta
Classifier: Intended Audience :: Developers
Classifier: License :: OSI Approved :: MIT License
Classifier: Operating System :: OS Independent
Classifier: Programming Language :: Python :: 3
Classifier: Programming Language :: Python :: 3.12
Classifier: Programming Language :: Python :: 3.13
Classifier: Programming Language :: Python :: 3.14
Classifier: Topic :: Software Development :: Libraries :: Python Modules
Requires-Dist: returns>=0.20,<0.27
Requires-Dist: fastapi==0.121.* ; extra == 'fastapi'
Requires-Dist: pydantic==2.* ; extra == 'fastapi'
Requires-Dist: numpy>=1.25,<3 ; extra == 'numpy'
Requires-Dist: ordered-set~=4.1 ; extra == 'ordered-set'
Requires-Python: >=3.12
Project-URL: Repository, https://github.com/drhagen/serialite
Provides-Extra: fastapi
Provides-Extra: numpy
Provides-Extra: ordered-set
